sed/P08908_ECFP12_1024_Top300.csv
sed/__init__.py
sed/demo_new.py
sed/dpc_screening.py
sed/gen_ecfp.py
sed/rf_test.py
sed/sed_common.py
sed/slep.py
sed/utils.py
sed_ecfp-0.0.5.dist-info/LICENSE
sed_ecfp-0.0.5.dist-info/METADATA
sed_ecfp-0.0.5.dist-info/WHEEL
sed_ecfp-0.0.5.dist-info/top_level.txt
sed_ecfp-0.0.5.dist-info/RECORD
