Metadata-Version: 2.1
Name: sed-ecfp
Version: 0.0.5
Summary: Predicting Bioactivities of Ligand Molecules Targeting G Protein-coupled Receptors by Merging Sparse Screening of Extended Connectivity Fingerprints and Deep Neural Nets
Home-page: UNKNOWN
Author: xhj
License: UNKNOWN
Platform: UNKNOWN
Classifier: Programming Language :: Python :: 3
Classifier: License :: OSI Approved :: MIT License
Classifier: Operating System :: OS Independent
Requires-Python: >=3.5
Requires-Dist: autograd (>=1.3)
Requires-Dist: numpy (>=1.18.5)
Requires-Dist: pandas (>=1.0.5)
Requires-Dist: scipy (>=1.2.1)
Requires-Dist: scikit-learn (>=0.23.1)
